__init__.py
sb_db_common/__init__.py
sb_db_common/config_base.py
sb_db_common/connection_base.py
sb_db_common/exceptions.py
sb_db_common/managed_cursor.py
sb_db_common/mssql_connection.py
sb_db_common/mysql_connection.py
sb_db_common/pgsql_connection.py
sb_db_common/session.py
sb_db_common/session_factory.py
sb_db_common/sqlite_connection.py
sb_db_common/utils.py
sb_db_common-0.1.0.dist-info/licenses/LICENSE
sb_db_common-0.1.0.dist-info/METADATA
sb_db_common-0.1.0.dist-info/WHEEL
sb_db_common-0.1.0.dist-info/top_level.txt
sb_db_common-0.1.0.dist-info/RECORD
