Metadata-Version: 2.4
Name: sb_db_common
Version: 0.1.0
Summary: A set of db wrappers
Author-email: Stephen Booth <stephen.booth.za@gmail.com>
Project-URL: homepage, https://github.com/sboothza/dbcommon
Classifier: Programming Language :: Python :: 3
Classifier: License :: OSI Approved :: MIT License
Classifier: Operating System :: OS Independent
Requires-Python: >=3.12
License-File: LICENSE
Requires-Dist: psycopg2-binary>=2.9.10
Requires-Dist: mysql-connector-python>=9.4.0
Requires-Dist: pymssql>=2.3.7
Requires-Dist: protobuf>=6.32.1
Dynamic: license-file
